.gitignore
MANIFEST.in
README.txt
setup.cfg
setup.py
cs/__init__.py
cs.rtmpstreaming.egg-info/PKG-INFO
cs.rtmpstreaming.egg-info/SOURCES.txt
cs.rtmpstreaming.egg-info/dependency_links.txt
cs.rtmpstreaming.egg-info/entry_points.txt
cs.rtmpstreaming.egg-info/namespace_packages.txt
cs.rtmpstreaming.egg-info/not-zip-safe
cs.rtmpstreaming.egg-info/paster_plugins.txt
cs.rtmpstreaming.egg-info/requires.txt
cs.rtmpstreaming.egg-info/top_level.txt
cs/rtmpstreaming/__init__.py
cs/rtmpstreaming/configure.zcml
cs/rtmpstreaming/rebuild_i18n.sh
cs/rtmpstreaming/tests.py
cs/rtmpstreaming/browser/__init__.py
cs/rtmpstreaming/browser/configure.zcml
cs/rtmpstreaming/browser/streamingview.pt
cs/rtmpstreaming/browser/streamingview.py
cs/rtmpstreaming/locales/cs.rtmpstreaming-manual.pot
cs/rtmpstreaming/locales/cs.rtmpstreaming.pot
cs/rtmpstreaming/locales/es/LC_MESSAGES/README.txt
cs/rtmpstreaming/locales/es/LC_MESSAGES/cs.rtmpstreaming.po
cs/rtmpstreaming/locales/eu/LC_MESSAGES/README.txt
cs/rtmpstreaming/locales/eu/LC_MESSAGES/cs.rtmpstreaming.po
cs/rtmpstreaming/portlets/__init__.py
cs/rtmpstreaming/portlets/configure.zcml
cs/rtmpstreaming/portlets/streamingportlet.pt
cs/rtmpstreaming/portlets/streamingportlet.py
cs/rtmpstreaming/profiles/default/jsregistry.xml
cs/rtmpstreaming/profiles/default/metadata.xml
cs/rtmpstreaming/profiles/default/portlets.xml
cs/rtmpstreaming/profiles/default/properties.xml
cs/rtmpstreaming/profiles/default/types.xml
cs/rtmpstreaming/profiles/default/types/Folder.xml
cs/rtmpstreaming/resources/jwplayer.js
cs/rtmpstreaming/resources/player.swf
cs/rtmpstreaming/tests/__init__.py
cs/rtmpstreaming/tests/base_streamingportlet.py
cs/rtmpstreaming/tests/test_streamingportlet.py
docs/HISTORY.txt
docs/INSTALL.txt
docs/LICENSE.GPL
docs/LICENSE.txt