Metadata-Version: 1.1
Name: cs.rtmpstreaming
Version: 1.0.4
Summary: A product to add a portlet that shows a RTMP streaming server image and audio using jwplayer
Home-page: http://github.com/codesyntax/cs.rtmpstreaming/
Author: Mikel Larreategi
Author-email: mlarreategi@codesyntax.com
License: GPL
Platform: UNKNOWN
Classifier: Framework :: Plone
Classifier: Programming Language :: Python
